{
  "id": "experiments.experiment-cloning",
  "identity": {
    "catalog_id": "experiments.experiment-cloning",
    "logical_id": "experiments.experiment-cloning",
    "source_id": "service:6db7472cbe25397f",
    "display_name": "ExperimentCloningService",
    "aliases": [
      "experiments.experiment-cloning",
      "services.experiments.cloning.ExperimentCloningService"
    ]
  },
  "module": "services.experiments.cloning",
  "class_name": "ExperimentCloningService",
  "qualified_name": "services.experiments.cloning.ExperimentCloningService",
  "description": "Service for cloning experiments with customization options",
  "docstring": "Service for cloning experiments with customization options",
  "source": {
    "file": "services/experiments/cloning.py",
    "line_start": 25,
    "line_end": 349
  },
  "operations": [
    {
      "id": "experiments.experiment-cloning.operation.clone_experiment",
      "identity": {
        "catalog_id": "experiments.experiment-cloning.operation.clone_experiment",
        "logical_id": "experiments.experiment-cloning.operation.clone_experiment",
        "source_id": "operation:9d1a9936c9f10647",
        "display_name": "ExperimentCloningService.clone_experiment",
        "aliases": [
          "experiments.experiment-cloning.operation.clone_experiment",
          "services.experiments.cloning.ExperimentCloningService.clone_experiment"
        ]
      },
      "method": "clone_experiment",
      "qualified_name": "services.experiments.cloning.ExperimentCloningService.clone_experiment",
      "parameters": [
        {
          "name": "org_id",
          "annotation": "UUID",
          "default": null,
          "kind": "positional_or_keyword"
        },
        {
          "name": "source_experiment_id",
          "annotation": "UUID",
          "default": null,
          "kind": "positional_or_keyword"
        },
        {
          "name": "clone_options",
          "annotation": "dict[str, Any]",
          "default": null,
          "kind": "positional_or_keyword"
        },
        {
          "name": "user_id",
          "annotation": "UUID",
          "default": null,
          "kind": "positional_or_keyword"
        }
      ],
      "returns": "dict[str, Any]",
      "description": "Clone an experiment with specified options",
      "docstring": "Clone an experiment with specified options\n\nArgs:\n    org_id: Organization ID\n    source_experiment_id: Experiment to clone\n    clone_options: Cloning configuration\n    user_id: User performing the clone\n    \nReturns:\n    Cloned experiment details",
      "source": {
        "file": "services/experiments/cloning.py",
        "line_start": 31,
        "line_end": 125
      },
      "detection": {
        "method": "public_method_in_service_class",
        "rule": "public_method_in_service_class",
        "confidence": "high",
        "evidence": [
          "method_name=clone_experiment",
          "qualified_name=services.experiments.cloning.ExperimentCloningService.clone_experiment"
        ]
      },
      "review_status": "generated"
    },
    {
      "id": "experiments.experiment-cloning.operation.get_cloneable_experiments",
      "identity": {
        "catalog_id": "experiments.experiment-cloning.operation.get_cloneable_experiments",
        "logical_id": "experiments.experiment-cloning.operation.get_cloneable_experiments",
        "source_id": "operation:1b357b59aa74416e",
        "display_name": "ExperimentCloningService.get_cloneable_experiments",
        "aliases": [
          "experiments.experiment-cloning.operation.get_cloneable_experiments",
          "services.experiments.cloning.ExperimentCloningService.get_cloneable_experiments"
        ]
      },
      "method": "get_cloneable_experiments",
      "qualified_name": "services.experiments.cloning.ExperimentCloningService.get_cloneable_experiments",
      "parameters": [
        {
          "name": "org_id",
          "annotation": "UUID",
          "default": null,
          "kind": "positional_or_keyword"
        },
        {
          "name": "user_id",
          "annotation": "UUID",
          "default": null,
          "kind": "positional_or_keyword"
        },
        {
          "name": "include_archived",
          "annotation": "bool",
          "default": "False",
          "kind": "positional_or_keyword"
        }
      ],
      "returns": "list[dict[str, Any]]",
      "description": "Get list of experiments that can be cloned",
      "docstring": "Get list of experiments that can be cloned",
      "source": {
        "file": "services/experiments/cloning.py",
        "line_start": 273,
        "line_end": 304
      },
      "detection": {
        "method": "public_method_in_service_class",
        "rule": "public_method_in_service_class",
        "confidence": "high",
        "evidence": [
          "method_name=get_cloneable_experiments",
          "qualified_name=services.experiments.cloning.ExperimentCloningService.get_cloneable_experiments"
        ]
      },
      "review_status": "generated"
    }
  ],
  "detection": {
    "method": "rule",
    "rule": "class_suffix_and_service_path",
    "confidence": "high",
    "evidence": [
      "class_name=ExperimentCloningService",
      "source_path=services/experiments/cloning.py"
    ]
  },
  "review_status": "generated"
}